chug/__init__.py
chug/torchdata/__init__.py
chug/webdataset/__init__.py
chug-0.0.0.dist-info/METADATA
chug-0.0.0.dist-info/WHEEL
chug-0.0.0.dist-info/top_level.txt
chug-0.0.0.dist-info/RECORD
